bit8_alu.v
`timescale 1ns/1ps

module bit8_alu(input[7:0] i1, input[7:0] i2, input[3:0] sel, output reg[8:0] o1);
	always @(*) begin
		case (sel)
			4'b0000: o1 = i1 + i2;                   // Addition
			4'b0001: o1 = i1 - i2;                   // Subtraction
			4'b0010: o1 = {1'b0, i1 | i2};           // OR
			4'b0011: o1 = {1'b0, i1 & i2};           // AND
			4'b0100: o1 = {1'b0, i1 ^ i2};           // XOR
			4'b0101: o1 = {1'b0, ~i1};               // NOT of 1st Input
			4'b0110: o1 = {1'b0, ~i2};               // NOT of 2nd Input
			4'b0111: o1 = {1'b0, ~(i1 | i2)};        // NOR
			4'b1000: o1 = {1'b0, ~(i1 & i2)};        // NAND
			4'b1001: o1 = {1'b0, ~(i1 ^ i2)};        // XNOR
			4'b1010: o1 = {1'b0, i1} >> 1;           // Shift Right 1st Input by 1bit
			4'b1011: o1 = {1'b0, i2} >> 1;           // Shift Right 2nd Input by 1bit
			4'b1100: o1 = {1'b0, i1} << 1;           // Shift Left 1st Input by 1bit
			4'b1101: o1 = {1'b0, i2} << 1;           // Shift Left 2nd Input by 1bit
			4'b1110: o1 = {1'b0, i1[1:0], i1[7:2]};  // Rotate right i1 by 2 bits
			4'b1111: o1 = {1'b0, i2[1:0], i2[7:2]};  // Rotate right i2 by 2 bits
			default: o1 = 9'b000000000;
		endcase
	end
endmodule

bit8_alu_tb.v
`timescale 1ns/1ps

module bit8_alu_tb;
	reg[7:0] a;
	reg[7:0] b;
	reg[3:0] ctrl;
	wire[8:0] o1;
	
	bit8_alu A1(.i1(a), .i2(b), .sel(ctrl), .o1(o1));
	
	initial begin
		a = 8'b00000000;
		b = 8'b00000000;
		ctrl = 4'b0000;
		
		$dumpfile("bit8_alu_wf.vcd");
		$dumpvars(0, bit8_alu_tb);
		
		#10 a = 8'b10110101;
		    b = 8'b11100111;
			
		#10 ctrl = 4'b0001;
		#10 ctrl = 4'b0010;
		#10 ctrl = 4'b0011;
		#10 ctrl = 4'b0100;
		#10 ctrl = 4'b0101;
		#10 ctrl = 4'b0110;
		#10 ctrl = 4'b0111;
		#10 ctrl = 4'b1000;
		#10 ctrl = 4'b1001;
		#10 ctrl = 4'b1010;
		#10 ctrl = 4'b1011;
		#10 ctrl = 4'b1100;
		#10 ctrl = 4'b1101;
		#10 ctrl = 4'b1110;
		#10 ctrl = 4'b1111;
		#10 ctrl = 4'b0000;
		
		#20;
		$finish;
	end
endmodule

bit8_alu_wf.vcd
$date
	Mon Oct 27 01:12:28 2025
$end
$version
	Icarus Verilog
$end
$timescale
	1ps
$end
$scope module bit8_alu_tb $end
$var wire 9 ! o1 [8:0] $end
$var reg 8 " a [7:0] $end
$var reg 8 # b [7:0] $end
$var reg 4 $ ctrl [3:0] $end
$scope module A1 $end
$var wire 8 % i1 [7:0] $end
$var wire 8 & i2 [7:0] $end
$var wire 4 ' sel [3:0] $end
$var reg 9 ( o1 [8:0] $end
$upscope $end
$upscope $end
$enddefinitions $end
#0
$dumpvars
b0 (
b0 '
b0 &
b0 %
b0 $
b0 #
b0 "
b0 !
$end
#10000
b110011100 !
b110011100 (
b11100111 #
b11100111 &
b10110101 "
b10110101 %
#20000
b111001110 !
b111001110 (
b1 $
b1 '
#30000
b11110111 !
b11110111 (
b10 $
b10 '
#40000
b10100101 !
b10100101 (
b11 $
b11 '
#50000
b1010010 !
b1010010 (
b100 $
b100 '
#60000
b1001010 !
b1001010 (
b101 $
b101 '
#70000
b11000 !
b11000 (
b110 $
b110 '
#80000
b1000 !
b1000 (
b111 $
b111 '
#90000
b1011010 !
b1011010 (
b1000 $
b1000 '
#100000
b10101101 !
b10101101 (
b1001 $
b1001 '
#110000
b1011010 !
b1011010 (
b1010 $
b1010 '
#120000
b1110011 !
b1110011 (
b1011 $
b1011 '
#130000
b101101010 !
b101101010 (
b1100 $
b1100 '
#140000
b111001110 !
b111001110 (
b1101 $
b1101 '
#150000
b1101101 !
b1101101 (
b1110 $
b1110 '
#160000
b11111001 !
b11111001 (
b1111 $
b1111 '
#170000
b110011100 !
b110011100 (
b0 $
b0 '
